pies-2.6.7.dist-info/top_level.txt
pies-2.6.7.dist-info/METADATA
pies-2.6.7.dist-info/RECORD
pies-2.6.7.dist-info/DESCRIPTION.rst
pies-2.6.7.dist-info/metadata.json
pies-2.6.7.dist-info/WHEEL
pies/imp.py
pies/unittest.py
pies/_utils.py
pies/sys.py
pies/collections.py
pies/functools.py
pies/ast.py
pies/itertools.py
pies/overrides.py
pies/__init__.py
pies/StringIO.py
pies/pickle.py
pies/version_info.py
